miniapi3/__init__.py
miniapi3/core.py
miniapi3/middleware.py
miniapi3/parameter_resolver.py
miniapi3/request.py
miniapi3/response.py
miniapi3/router.py
miniapi3/server.py
miniapi3/utils.py
miniapi3/validation.py
miniapi3/websocket.py
miniapi3/handlers/__init__.py
miniapi3/handlers/base_handler.py
miniapi3/handlers/http_handler.py
miniapi3/handlers/raw_handler.py
miniapi3/handlers/websocket_handler.py
miniapi3-0.1.7.dist-info/METADATA
miniapi3-0.1.7.dist-info/WHEEL
miniapi3-0.1.7.dist-info/top_level.txt
miniapi3-0.1.7.dist-info/RECORD
