Metadata-Version: 2.1
Name: miniapi3
Version: 0.1.7
Summary: miniapi like fastapi
Author-email: milisp <milisp@proton.me>
License: MIT
Requires-Python: >=3.9
Provides-Extra: websockets
Requires-Dist: websockets>=10.0; extra == "websockets"
Provides-Extra: uvicorn
Requires-Dist: uvicorn>=0.22.0; extra == "uvicorn"
Provides-Extra: pydantic
Requires-Dist: pydantic>=2.0.0; extra == "pydantic"
